two_numpy.py
two_numpy-0.1.0.dist-info/METADATA
two_numpy-0.1.0.dist-info/WHEEL
two_numpy-0.1.0.dist-info/top_level.txt
two_numpy-0.1.0.dist-info/RECORD
