Metadata-Version: 2.1
Name: two_numpy
Version: 0.1.0
Summary: A simple library for manager the numpy version to different python interpreters.
Home-page: https://github.com/Locked-chess-official/two_numpy
Author: Huang Hao Hua
Author-email: 13140752715@163.com
License: MIT
Requires-Python: >=3.13
Requires-Dist: numpy
Requires-Dist: packaging
